zhipuai/__init__.py
zhipuai/__version__.py
zhipuai/_client.py
zhipuai/api_resource/__init__.py
zhipuai/api_resource/agents/__init__.py
zhipuai/api_resource/agents/agents.py
zhipuai/api_resource/assistant/__init__.py
zhipuai/api_resource/assistant/assistant.py
zhipuai/api_resource/audio/__init__.py
zhipuai/api_resource/audio/audio.py
zhipuai/api_resource/audio/transcriptions.py
zhipuai/api_resource/batches.py
zhipuai/api_resource/chat/__init__.py
zhipuai/api_resource/chat/async_completions.py
zhipuai/api_resource/chat/chat.py
zhipuai/api_resource/chat/completions.py
zhipuai/api_resource/embeddings.py
zhipuai/api_resource/files.py
zhipuai/api_resource/fine_tuning/__init__.py
zhipuai/api_resource/fine_tuning/fine_tuning.py
zhipuai/api_resource/fine_tuning/jobs/__init__.py
zhipuai/api_resource/fine_tuning/jobs/jobs.py
zhipuai/api_resource/fine_tuning/models/__init__.py
zhipuai/api_resource/fine_tuning/models/fine_tuned_models.py
zhipuai/api_resource/images.py
zhipuai/api_resource/knowledge/__init__.py
zhipuai/api_resource/knowledge/document/__init__.py
zhipuai/api_resource/knowledge/document/document.py
zhipuai/api_resource/knowledge/knowledge.py
zhipuai/api_resource/moderation/__init__.py
zhipuai/api_resource/moderation/moderations.py
zhipuai/api_resource/tools/__init__.py
zhipuai/api_resource/tools/tools.py
zhipuai/api_resource/videos/__init__.py
zhipuai/api_resource/videos/videos.py
zhipuai/api_resource/web_search/__init__.py
zhipuai/api_resource/web_search/web_search.py
zhipuai/core/__init__.py
zhipuai/core/_base_api.py
zhipuai/core/_base_compat.py
zhipuai/core/_base_models.py
zhipuai/core/_base_type.py
zhipuai/core/_constants.py
zhipuai/core/_errors.py
zhipuai/core/_files.py
zhipuai/core/_http_client.py
zhipuai/core/_jwt_token.py
zhipuai/core/_legacy_binary_response.py
zhipuai/core/_legacy_response.py
zhipuai/core/_request_opt.py
zhipuai/core/_response.py
zhipuai/core/_sse_client.py
zhipuai/core/_utils/__init__.py
zhipuai/core/_utils/_transform.py
zhipuai-2.1.5.20250726.dist-info/LICENSE
zhipuai-2.1.5.20250726.dist-info/METADATA
zhipuai-2.1.5.20250726.dist-info/WHEEL
zhipuai-2.1.5.20250726.dist-info/RECORD
